AUTHORS.md
CHANGELOG.md
MANIFEST.in
README
README.md
setup.cfg
setup.py
systranio/Translation.py
systranio/__init__.py
systranio/api.py
systranio/exceptions.py
systranio/utils.py
systranio.egg-info/PKG-INFO
systranio.egg-info/SOURCES.txt
systranio.egg-info/dependency_links.txt
systranio.egg-info/requires.txt
systranio.egg-info/top_level.txt