Metadata-Version: 1.1
Name: systranio
Version: 0.6.0
Summary: A simple REST API client for Systran.io
Home-page: https://gitlab.com/canarduck/systranio
Author: Canarduck
Author-email: renaud@canarduck.com
License: UNKNOWN
Keywords: api rest systran translation
Platform: UNKNOWN
Classifier: Programming Language :: Python :: 3
Classifier: Development Status :: 3 - Alpha
Classifier: Environment :: Web Environment
Classifier: Intended Audience :: Developers
Classifier: License :: OSI Approved :: MIT License
Classifier: Operating System :: OS Independent
Classifier: Topic :: Software Development :: Libraries :: Python Modules
Classifier: Topic :: Text Processing :: Linguistic
